{
  "experiment": "E6 directions",
  "layer": 28,
  "per_letter": {
    "n_letters": 18,
    "min_support": 20,
    "mean_norm": 87.23320770263672,
    "mean_pairwise_cosine": -0.04060888662934303,
    "letters": [
      "A",
      "B",
      "C",
      "D",
      "E",
      "F",
      "G",
      "H",
      "I",
      "M",
      "N",
      "O",
      "P",
      "R",
      "S",
      "T",
      "V",
      "W"
    ]
  },
  "encoding_mode": {
    "n_pairs": 180,
    "norm": 157.25881958007812
  }
}